aws_orbit_jupyterlab_orbit-1.4.0.data/data/etc/jupyter/jupyter_server_config.d/jupyterlab_orbit.json
aws_orbit_jupyterlab_orbit-1.4.0.data/data/share/jupyter/labextensions/jupyterlab_orbit/install.json
aws_orbit_jupyterlab_orbit-1.4.0.data/data/share/jupyter/labextensions/jupyterlab_orbit/package.json
aws_orbit_jupyterlab_orbit-1.4.0.data/data/share/jupyter/labextensions/jupyterlab_orbit/static/133.261a283510a61af420ed.js
aws_orbit_jupyterlab_orbit-1.4.0.data/data/share/jupyter/labextensions/jupyterlab_orbit/static/133.261a283510a61af420ed.js.LICENSE.txt
aws_orbit_jupyterlab_orbit-1.4.0.data/data/share/jupyter/labextensions/jupyterlab_orbit/static/171.cd23c3af7a3a4d58dd4b.js
aws_orbit_jupyterlab_orbit-1.4.0.data/data/share/jupyter/labextensions/jupyterlab_orbit/static/258.31ab080414756b4409df.js
aws_orbit_jupyterlab_orbit-1.4.0.data/data/share/jupyter/labextensions/jupyterlab_orbit/static/35.debde168abde1938a84c.js
aws_orbit_jupyterlab_orbit-1.4.0.data/data/share/jupyter/labextensions/jupyterlab_orbit/static/35.debde168abde1938a84c.js.LICENSE.txt
aws_orbit_jupyterlab_orbit-1.4.0.data/data/share/jupyter/labextensions/jupyterlab_orbit/static/545.318f2c329409da33b7fa.js
aws_orbit_jupyterlab_orbit-1.4.0.data/data/share/jupyter/labextensions/jupyterlab_orbit/static/545.318f2c329409da33b7fa.js.LICENSE.txt
aws_orbit_jupyterlab_orbit-1.4.0.data/data/share/jupyter/labextensions/jupyterlab_orbit/static/549.1bc979575ab783cac282.js
aws_orbit_jupyterlab_orbit-1.4.0.data/data/share/jupyter/labextensions/jupyterlab_orbit/static/597.a1a3bb0f26f233729211.js
aws_orbit_jupyterlab_orbit-1.4.0.data/data/share/jupyter/labextensions/jupyterlab_orbit/static/614.748760d0395687eba589.js
aws_orbit_jupyterlab_orbit-1.4.0.data/data/share/jupyter/labextensions/jupyterlab_orbit/static/700.184dc64b981673d2b8ed.js
aws_orbit_jupyterlab_orbit-1.4.0.data/data/share/jupyter/labextensions/jupyterlab_orbit/static/762.d8621af3ef1b42b8c2fa.js
aws_orbit_jupyterlab_orbit-1.4.0.dist-info/METADATA
aws_orbit_jupyterlab_orbit-1.4.0.dist-info/WHEEL
aws_orbit_jupyterlab_orbit-1.4.0.dist-info/top_level.txt
aws_orbit_jupyterlab_orbit-1.4.0.dist-info/RECORD
