Metadata-Version: 2.1
Name: aws-orbit-jupyterlab-orbit
Version: 1.4.0
Summary: AWS Orbit Workbench JupyterLab extension.
Home-page: https://github.com/awslabs/aws-orbit-workbench
Author: AWS Professional Services
Author-email: aws-proserve-opensource@amazon.com
License: Apache License 2.0
Project-URL: Org Site, https://aws.amazon.com/professional-services/
Keywords: Jupyter,JupyterLab,JupyterLab3
Platform: Linux
Platform: Mac OS X
Platform: Windows
Classifier: Programming Language :: Python
Classifier: Programming Language :: Python :: 3
Classifier: Programming Language :: Python :: 3.7
Classifier: Programming Language :: Python :: 3.8
Classifier: Framework :: Jupyter
Requires-Python: >=3.7
Requires-Dist: jupyterlab (==3.*,>=3.0.0rc13)
